{"assets":[{"id":"4","layers":[{"ind":3,"ty":4,"ks":{},"ip":0,"op":181,"st":0,"shapes":[{"ty":"rc","p":{"a":0,"k":[4,5.5]},"r":{"a":0,"k":0},"s":{"a":0,"k":[8,11]}},{"ty":"fl","c":{"a":0,"k":[0,0,0,0]},"o":{"a":0,"k":0}}]},{"ind":0,"ty":4,"ks":{"s":{"a":0,"k":[133.33,133.33]}},"ip":0,"op":181,"st":0,"shapes":[{"ty":"gr","it":[{"ty":"gr","it":[{"ty":"sh","ks":{"a":0,"k":{"c":true,"i":[[0,0],[0,0],[0.23,-0.23],[0.23,0.23],[0,0],[0,0],[0.33,0],[0,0.33],[0,0],[0,0],[0.23,0.23],[-0.23,0.23],[0,0]],"o":[[0,0],[0.23,0.23],[-0.23,0.23],[0,0],[0,0],[0,0.33],[-0.33,0],[0,0],[0,0],[-0.23,0.23],[-0.23,-0.23],[0,0],[0,0]],"v":[[3.27,0.43],[5.52,2.68],[5.52,3.52],[4.68,3.52],[3.45,2.3],[3.45,7.22],[2.85,7.82],[2.25,7.22],[2.25,2.3],[1.02,3.52],[0.18,3.52],[0.18,2.68],[2.85,0]]}}},{"ty":"fl","c":{"a":0,"k":[1,1,1,1]},"o":{"a":0,"k":100}},{"ty":"tr","o":{"a":0,"k":100}}]},{"ty":"tr","o":{"a":0,"k":100}}]}]}]},{"id":"7","layers":[{"ind":6,"ty":0,"ks":{},"w":8,"h":11,"ip":0,"op":181,"st":0,"refId":"4"}]},{"id":"13","layers":[{"ind":12,"ty":4,"ks":{},"ip":0,"op":181,"st":0,"shapes":[{"ty":"rc","p":{"a":0,"k":[19,6]},"r":{"a":0,"k":0},"s":{"a":0,"k":[38,12]}},{"ty":"fl","c":{"a":0,"k":[0,0,0,0]},"o":{"a":0,"k":0}}]},{"ind":0,"ty":4,"ks":{"s":{"a":0,"k":[133.33,133.33]}},"ip":0,"op":181,"st":0,"shapes":[{"ty":"gr","it":[{"ty":"gr","it":[{"ty":"sh","ks":{"a":0,"k":{"c":true,"i":[[0,0],[0,0],[-0.19,-0.44],[-1.11,0],[0,0],[-0.45,1.02],[-0.48,0],[0,0],[0,-0.66],[0,0],[1.77,0],[0,0],[0,1.77],[0,0],[-0.66,0]],"o":[[0,0],[0.48,0],[0.45,1.02],[0,0],[1.11,0],[0.19,-0.44],[0,0],[0.66,0],[0,0],[0,1.77],[0,0],[-1.77,0],[0,0],[0,-0.66],[0,0]],"v":[[2,0.8],[12.41,0.8],[13.52,1.52],[16.09,3.2],[21.91,3.2],[24.48,1.52],[25.59,0.8],[36,0.8],[37.2,2],[37.2,8],[34,11.2],[4,11.2],[0.8,8],[0.8,2],[2,0.8]]}}},{"ty":"st","c":{"a":0,"k":[1,1,1,1]},"lc":1,"lj":1,"ml":4,"o":{"a":0,"k":100},"w":{"a":0,"k":1.6}},{"ty":"tr","o":{"a":0,"k":100},"s":{"a":0,"k":[75,75]}}]},{"ty":"gr","it":[{"ty":"sh","ks":{"a":0,"k":{"c":true,"i":[[0,0],[0,0],[-0.14,-0.33],[-0.84,0],[0,0],[-0.34,0.77],[-0.36,0],[0,0],[0,-0.5],[0,0],[1.32,0],[0,0],[0,1.32],[0,0],[-0.5,0]],"o":[[0,0],[0.36,0],[0.34,0.77],[0,0],[0.84,0],[0.14,-0.33],[0,0],[0.5,0],[0,0],[0,1.32],[0,0],[-1.32,0],[0,0],[0,-0.5],[0,0]],"v":[[1.5,0.6],[9.31,0.6],[10.14,1.14],[12.07,2.4],[16.43,2.4],[18.36,1.14],[19.19,0.6],[27,0.6],[27.9,1.5],[27.9,6],[25.5,8.4],[3,8.4],[0.6,6],[0.6,1.5],[1.5,0.6]]}}},{"ty":"fl","c":{"a":0,"k":[0.09,0.09,0.09,1]},"o":{"a":0,"k":100}},{"ty":"tr","o":{"a":0,"k":100}}]},{"ty":"tr","o":{"a":0,"k":100}}]}]}]}],"fr":60,"h":48,"ip":0,"layers":[{"ind":9,"ty":0,"parent":2,"ks":{"o":{"a":1,"k":[{"t":0,"s":[0],"h":1},{"t":80.4,"s":[0],"i":{"x":1,"y":1},"o":{"x":0,"y":0}},{"t":97.8,"s":[100],"h":1},{"t":126.6,"s":[100],"i":{"x":1,"y":1},"o":{"x":0,"y":0}},{"t":156,"s":[0],"h":1},{"t":180,"s":[0],"h":1}]},"p":{"a":1,"k":[{"t":0,"s":[15,17],"i":{"x":[1,1],"y":[1,1]},"o":{"x":[0,0],"y":[0,0]}},{"t":60,"s":[15,17],"i":{"x":[1,1],"y":[1,1]},"o":{"x":[0,1],"y":[0,0]}},{"t":90,"s":[15,7],"i":{"x":[1,1],"y":[1,1]},"o":{"x":[0,0],"y":[0,0]}},{"t":126.6,"s":[15,7],"i":{"x":[1,1],"y":[1,1]},"o":{"x":[0,1],"y":[0,0]}},{"t":156,"s":[15,-3],"i":{"x":[1,1],"y":[1,1]},"o":{"x":[0,0],"y":[0,0]}},{"t":180,"s":[15,-3],"h":1}]}},"w":8,"h":11,"ip":0,"op":181,"st":0,"refId":"7"},{"ind":15,"ty":0,"parent":11,"ks":{},"w":38,"h":12,"ip":0,"op":181,"st":0,"refId":"13"},{"ind":11,"ty":3,"parent":10,"ks":{"p":{"a":0,"k":[0,21]}},"ip":0,"op":181,"st":0},{"ind":18,"ty":4,"td":1,"parent":16,"ks":{},"ip":0,"op":181,"st":0,"shapes":[{"ty":"rc","p":{"a":0,"k":[16,12.5]},"r":{"a":0,"k":4},"s":{"a":0,"k":[32,25]}},{"ty":"fl","c":{"a":0,"k":[0,0,0]},"o":{"a":0,"k":100}}]},{"ind":17,"ty":4,"tt":1,"parent":16,"ks":{},"ip":0,"op":181,"st":0,"shapes":[{"ty":"gr","it":[{"ty":"rc","p":{"a":0,"k":[16,12.5]},"r":{"a":0,"k":0},"s":{"a":0,"k":[35.2,28.2]}},{"ty":"fl","c":{"a":0,"k":[0,0,0,0]},"o":{"a":0,"k":0}},{"ty":"tr","o":{"a":0,"k":100}}]},{"ty":"gr","it":[{"ty":"rc","p":{"a":0,"k":[16,12.5]},"r":{"a":0,"k":4},"s":{"a":0,"k":[32,25]}},{"ty":"st","c":{"a":0,"k":[1,1,1]},"lc":1,"lj":1,"ml":10,"o":{"a":0,"k":100},"w":{"a":0,"k":3.2}},{"ty":"tr","o":{"a":0,"k":100}}]}]},{"ind":16,"ty":3,"parent":10,"ks":{"p":{"a":0,"k":[3,0]}},"ip":0,"op":181,"st":0},{"ind":10,"ty":3,"parent":2,"ks":{"a":{"a":0,"k":[19,16.5]},"p":{"a":1,"k":[{"t":0,"s":[19,12.5],"i":{"x":[1,1],"y":[1,1]},"o":{"x":[0,0],"y":[0,0]}},{"t":18,"s":[19,12.5],"i":{"x":[1,0.741],"y":[1,0.482]},"o":{"x":[0,0.4],"y":[0,0]}},{"t":23.988,"s":[19,16.5],"i":{"x":[1,0.679],"y":[1,0.999]},"o":{"x":[0,0.347],"y":[0,0.693]}},{"t":26.982,"s":[19,15.499],"i":{"x":[1,0.733],"y":[1,0.466]},"o":{"x":[0,0.394],"y":[0,0.001]}},{"t":29.982,"s":[19,16.5],"i":{"x":[1,0.608],"y":[1,0.998]},"o":{"x":[0,0.27],"y":[0,0.539]}},{"t":31.476,"s":[19,16.249],"i":{"x":[1,0.564],"y":[1,0.129]},"o":{"x":[0,0.214],"y":[0,0.001]}},{"t":32.976,"s":[19,16.5],"i":{"x":[1,0.583],"y":[1,0.998]},"o":{"x":[0,0.236],"y":[0,0.473]}},{"t":33.732,"s":[19,16.437],"i":{"x":[1,0.533],"y":[1,0.07]},"o":{"x":[0,0.17],"y":[0,0.002]}},{"t":34.482,"s":[19,16.5],"i":{"x":[1,0.971],"y":[1,1]},"o":{"x":[0,0.539],"y":[0,1]}},{"t":34.86,"s":[19,16.484],"i":{"x":[1,0.454],"y":[1,0]},"o":{"x":[0,0.011],"y":[0,0]}},{"t":35.238,"s":[19,16.5],"i":{"x":[1,1],"y":[1,1]},"o":{"x":[0,0],"y":[0,0]}},{"t":35.43,"s":[19,16.496],"i":{"x":[1,1],"y":[1,1]},"o":{"x":[0,0],"y":[0,0]}},{"t":35.616,"s":[19,16.5],"i":{"x":[1,1],"y":[1,1]},"o":{"x":[0,0],"y":[0,0]}},{"t":180,"s":[19,16.5],"h":1}]},"r":{"a":1,"k":[{"t":0,"s":[15],"i":{"x":0.75,"y":1},"o":{"x":0.35,"y":0}},{"t":5.4,"s":[20],"i":{"x":0.2,"y":1},"o":{"x":0.25,"y":0}},{"t":18,"s":[-10],"i":{"x":0.75,"y":1},"o":{"x":0.35,"y":0}},{"t":23.4,"s":[-12],"i":{"x":0.2,"y":1},"o":{"x":0.25,"y":0}},{"t":36,"s":[0],"h":1},{"t":180,"s":[0],"h":1}]}},"ip":0,"op":181,"st":0},{"ind":2,"ty":3,"parent":1,"ks":{"p":{"a":0,"k":[5,7]}},"ip":0,"op":181,"st":0},{"ind":20,"ty":4,"parent":19,"ks":{},"ip":0,"op":181,"st":0,"shapes":[{"ty":"rc","p":{"a":0,"k":[24,23.575]},"r":{"a":0,"k":0},"s":{"a":0,"k":[48,47.151]}},{"ty":"fl","c":{"a":0,"k":[1,0.102,0.102,0]},"o":{"a":0,"k":0}}]},{"ind":19,"ty":3,"parent":1,"ks":{"p":{"a":0,"k":[0,0]}},"ip":0,"op":181,"st":0},{"ind":1,"ty":3,"parent":0,"ks":{},"ip":0,"op":181,"st":0},{"ind":21,"ty":4,"parent":0,"ks":{},"ip":0,"op":181,"st":0,"shapes":[{"ty":"rc","p":{"a":0,"k":[24,23.575]},"r":{"a":0,"k":0},"s":{"a":0,"k":[48,47.151]}},{"ty":"fl","c":{"a":0,"k":[0.788,0.788,0.788,0]},"o":{"a":0,"k":0}}]},{"ind":0,"ty":3,"ks":{},"ip":0,"op":181,"st":0}],"meta":{"g":"https://jitter.video"},"op":180,"v":"5.7.4","w":48}